<C><P L="1068" D="x_transformice/x_evt/x_evt_05/yelfrdge/fond.jpg" mc="" Ca="" APS="x_transformice/x_evt/x_evt_05/yelfrdge/souche.png,0,420,80,480,400,371,0" /><Z><S><S Y="389" T="12" P="0,0,0.3,0.2,0,0,0,0" L="800" o="324650" m="" H="47" X="794" /><S Y="351" T="12" X="537" P="0,0,0.3,0.2,0,0,0,0" L="30" o="324650" m="" H="30" /><S Y="197" T="12" P="0,0,0.3,0.2,0,0,0,0" L="300" o="324650" m="" X="582" H="10" /><S Y="351" T="12" H="30" P="0,0,0.3,0.2,0,0,0,0" L="30" o="324650" m="" X="711" /><S Y="221" T="12" H="10" P="0,0,0.3,0.2,0,0,0,0" L="30" o="324650" m="" X="743" /><S Y="246" T="12" P="0,0,0.3,0.2,0,0,0,0" L="30" o="324650" m="" H="10" X="768" /><S Y="265" T="12" X="788" P="0,0,0.3,0.2,0,0,0,0" L="30" o="324650" m="" H="10" /><S Y="306" T="12" P="0,0,0.3,0.2,0,0,0,0" L="30" o="324650" m="" X="830" H="10" /><S Y="287" T="12" H="10" P="0,0,0.3,0.2,0,0,0,0" L="30" o="324650" m="" X="807" /><S Y="326" T="12" P="0,0,0.3,0.2,0,0,0,0" L="30" o="324650" m="" H="10" X="851" /><S Y="316" T="12" X="840" P="0,0,0.3,0.2,90,0,0,0" L="30" o="324650" m="" H="10" /><S Y="297" T="12" P="0,0,0.3,0.2,90,0,0,0" L="30" o="324650" m="" X="819" H="10" /><S Y="275" T="12" H="10" P="0,0,0.3,0.2,90,0,0,0" L="30" o="324650" m="" X="798" /><S Y="255" T="12" P="0,0,0.3,0.2,90,0,0,0" L="30" o="324650" m="" H="10" X="779" /><S Y="231" T="12" X="756" P="0,0,0.3,0.2,90,0,0,0" L="30" o="324650" m="" H="10" /><S Y="207" T="12" P="0,0,0.3,0.2,90,0,0,0" L="30" o="324650" m="" X="734" H="10" /><S Y="135" T="12" X="566" P="0,0,0.3,0.2,130,0,0,0" L="10" o="324650" m="" H="25" /><S Y="307" T="12" P="0,0,0.3,0.2,130,0,0,0" L="10" o="ff00f6" m="" X="919" H="60" /><S Y="316" T="12" H="60" P="0,0,0.3,0.2,120,0,0,0" L="10" o="ff00f6" m="" X="938" /><S Y="348" T="12" P="0,0,0.3,0.2,130,0,0,0" L="10" o="ff00f6" m="" H="60" X="983" /><S Y="274" T="12" X="907" P="0,0,0.3,0.2,160,0,0,0" L="10" o="ff00f6" m="" H="60" /><S Y="216" T="12" P="0,0,0.3,0.2,190,0,0,0" L="10" o="ff00f6" m="" X="902" H="60" /><S Y="185" T="12" H="60" P="0,0,0.3,0.2,230,0,0,0" L="10" o="ff00f6" m="" X="928" /><S Y="175" T="12" P="0,0,0.3,0.2,240,0,0,0" L="10" o="ff00f6" m="" H="60" X="931" /><S Y="176" T="12" X="939" P="0,0,0.3,0.2,240,0,0,0" L="10" o="ff00f6" m="" H="60" /><S Y="161" T="12" P="0,0,0.3,0.2,90,0,0,0" L="10" o="ff00f6" m="" X="959" H="10" /><S Y="111" T="12" H="60" P="0,0,0.3,0.2,250,0,0,0" L="10" o="db16cb" m="" X="927" /><S Y="267" T="12" P="0,0,0.3,0.2,180,0,0,0" L="10" o="ff00f6" m="" X="897" H="50" /><S Y="94" T="12" P="0,0,0.3,0.2,180,0,0,0" L="10" o="db16cb" m="" H="60" X="902" /><S Y="69" T="12" X="674" P="0,0,0.3,0.2,0,0,0,0" L="460" o="db16cb" m="" H="10" /><S Y="123" T="12" X="433" P="0,0,10,0.2,180,0,0,0" L="10" o="db16cb" m="" H="120" /><S Y="237" T="12" P="0,0,0.3,0.2,200,0,0,0" L="10" o="db16cb" m="" X="412" H="120" /><S Y="288" T="12" H="40" P="0,0,0.3,0.2,280,0,0,0" L="10" o="db16cb" m="" X="386" /><S Y="299" T="12" P="0,0,0.3,0.2,210,0,0,0" L="10" o="db16cb" m="" H="40" X="362" /><S Y="349" T="12" H="110" P="0,0,0.3,0.2,270,0,0,0" L="40" o="db16cb" m="" X="625" /><S Y="179" T="12" P="0,0,0.3,1,270,0,0,0" L="10" o="db16cb" m="" H="110" X="664" /><S Y="171" T="12" H="10" P="0,0,0.3,0.2,90,0,0,0" L="60" o="324650" m="" X="604" /><S Y="319" T="12" X="352" P="0,0,0.3,0.2,380,0,0,0" L="10" o="db16cb" m="" H="20" /><S Y="318" T="12" X="1027" P="0,0,0.3,1,270,0,0,0" L="10" o="db16cb" m="" H="40" /><S Y="331" T="12" P="0,0,0.3,1,320,0,0,0" L="10" o="db16cb" m="" X="1056" H="40" /><S Y="306" T="12" H="40" P="0,0,0.3,1,220,0,0,0" L="10" o="db16cb" m="" X="972" /><S Y="308" T="12" P="0,0,0.3,1,140,0,0,0" L="10" o="db16cb" m="" H="40" X="1009" /><S Y="293" T="12" X="991" P="0,0,0.3,1,90,0,0,0" L="10" o="db16cb" m="" H="20" /><S i="0,0,x_transformice/x_evt/x_evt_05/yelfrdge/bateau.png" T="12" X="472" P="1,0,0.3,0.2,0,0,0,0" Y="282" L="38" o="324650" H="23" /><S Y="171" T="12" X="1073" P="0,0,0,0.2,180,0,0,0" L="10" o="ff00f6" m="" H="400" /><S N="" Y="320" T="12" X="257" P="0,0,0.3,0.2,0,0,0,0" i="0,-15,x_transformice/x_evt/x_evt_05/yelfrdge/boite au lettre.png" L="45" o="324650" H="27" /><S N="" Y="118" T="12" X="460" P="0,0,0.3,0.2,0,0,0,0" i="-28,-25,x_transformice/x_evt/x_evt_05/yelfrdge/bougie1.png" L="10" o="ff0909" H="40" c="4" /><S N="" Y="323" T="12" H="35" P="0,0,0.3,0.2,0,0,0,0" i="-31,-25,x_transformice/x_evt/x_evt_05/yelfrdge/bougie2.png" L="10" o="ff0404" X="922" c="4" /><S i="-15,0,x_transformice/x_evt/x_evt_05/yelfrdge/chapeau.png" T="12" P="1,1,0.3,0.2,0,0,0,0" Y="248" L="25" o="324650" X="566" H="17" /><S N="" Y="240" T="12" P="1,0,0.3,0.2,0,0,0,0" i="-8,-25,x_transformice/x_evt/x_evt_05/yelfrdge/fleurs.png" L="14" o="324650" X="687" H="18" /><S Y="298" T="12" P="0,0,0.3,0.2,0,0,0,0" i="-10,0,x_transformice/x_evt/x_evt_05/yelfrdge/etagere1.png" L="55" o="324650" H="10" X="471" /><S Y="264" T="12" P="0,0,0.3,0.2,0,0,0,0" i="-12,0,x_transformice/x_evt/x_evt_05/yelfrdge/etgere2.png" L="67" o="324650" X="687" H="10" /><S N="" Y="173" T="12" H="34" P="1,0,0.3,0.2,0,0,0,0" i="-45,-42,x_transformice/x_evt/x_evt_05/yelfrdge/lampadaire.png" L="23" o="324650" X="817" /><S N="" i="-23,-10,x_transformice/x_evt/x_evt_05/yelfrdge/theiere.png" T="13" X="626" P="1,0,0.3,0.2,0,0,0,0" Y="315" L="12" o="324650" H="10" /><S N="" Y="18" T="12" P="0,0,0.3,0.2,0,0,0,0" i="0,0,x_transformice/x_evt/x_evt_05/yelfrdge/premier plan.png" L="66" o="324650" H="36" X="33" /><S N="" Y="337" T="12" X="162" P="0,0,0.3,0.2,0,0,0,0" i="0,0,x_transformice/x_evt/x_evt_05/yelfrdge/herbe4.png" L="67" o="324650" H="35" c="4" /><S N="" Y="284" T="12" X="97" P="0,0,0.3,0.2,0,0,0,0" i="0,0,x_transformice/x_evt/x_evt_05/yelfrdge/herbe2.png" L="67" o="324650" H="35" c="4" /><S N="" Y="157" T="12" X="10" P="0,0,0.3,0.2,0,0,0,0" i="0,0,x_transformice/x_evt/x_evt_05/yelfrdge/herbe1.png" L="50" o="324650" H="35" c="4" /><S N="" Y="85" T="12" H="35" P="0,0,0.3,0.2,0,0,0,0" i="0,0,x_transformice/x_evt/x_evt_05/yelfrdge/premier plan maison.png" L="67" o="324650" X="410" c="4" /><S i="-10,0,x_transformice/x_evt/x_evt_05/yelfrdge/etagere1.png" T="12" X="566" P="0,0,0.3,0.2,0,0,0,0" Y="264" L="55" o="324650" H="10" /><S Y="407" T="12" X="320" P="0,0,0.3,0.2,0,0,0,0" L="800" o="324650" m="" H="47" /><S N="" Y="139" T="12" H="20" P="1,0,0.3,0.2,0,0,0,0" i="4,0,x_transformice/x_evt/x_evt_05/yelfrdge/corde.png" L="10" o="324650" X="816" c="4" /><S N="" i="4,0,x_transformice/x_evt/x_evt_05/yelfrdge/corde.png" T="12" X="816" P="1,0,0.3,0.2,0,0,0,0" Y="123" L="10" o="324650" H="20" c="4" /><S N="" Y="106" T="12" X="816" P="1,0,0.3,0.2,0,0,0,0" i="4,0,x_transformice/x_evt/x_evt_05/yelfrdge/corde.png" L="10" o="324650" H="20" c="4" /><S N="" i="4,0,x_transformice/x_evt/x_evt_05/yelfrdge/corde.png" T="12" H="20" P="1,0,0.3,0.2,0,0,0,0" Y="89" L="10" o="324650" X="816" c="4" /><S Y="153" T="12" X="819" P="1,0,0.3,0.2,50,0,0,0" L="20" o="ff00f6" m="" H="10" c="4" /><S Y="153" T="12" P="1,0,0.3,0.2,120,0,0,0" H="10" L="20" o="ff00f6" m="" X="813" c="4" /><S i="-15,-15,x_transformice/x_evt/x_evt_05/yelfrdge/bocal.png" T="13" H="10" P="1,0,0.3,0.2,0,0,0,0" Y="112" L="15" o="324650" X="537" /><S N="" Y="315" T="12" H="35" P="0,0,0.3,0.2,0,0,0,0" i="0,0,x_transformice/x_evt/x_evt_05/yelfrdge/herbe3.png" L="67" o="22d90e" X="968" c="4" /><S Y="338" T="12" X="944" P="0,0,0.3,0.2,140,0,0,0" L="10" o="ff00f6" m="" H="60" /><S Y="189" T="12" P="0,0,0.3,0.2,90,0,0,0" L="30" o="324650" m="" H="10" X="717" /><S Y="132" T="12" P="0,0,0.3,0.2,85,0,0,0" L="10" o="324650" m="" X="533" H="55" /><S Y="168" T="12" H="60" P="0,0,0.3,0.2,175,0,0,0" L="10" o="324650" m="" X="513" /><S Y="169" T="12" P="0,0,0.3,0.2,190,0,0,0" L="10" o="324650" m="" H="60" X="569" /><S Y="130" T="12" X="528" P="0,0,0.3,0.2,105,0,0,0" L="10" o="c831ad" m="" H="10" c="2" /><S Y="80" T="12" P="0,0,0.3,0.2,0,0,0,0" L="200" o="db16cb" m="" X="678" H="10" /><S Y="74" T="12" H="10" P="0,0,0.3,0.2,5,0,0,0" L="150" o="db16cb" m="" X="505" /><S Y="75" T="12" P="0,0,0.3,0.2,-5,0,0,0" L="120" o="db16cb" m="" H="10" X="836" /><S Y="378" T="12" P="0,0,0.3,0.2,410,0,0,0" L="10" o="db16cb" m="" X="387" H="30" /><S Y="253" T="12" P="1,1,0.3,0.2,270,0,0,0" L="10" o="db16cb" m="" H="40" X="566" /><S Y="197" T="12" P="0,0,0,0.2,180,0,0,0" L="10" o="ff00f6" m="" X="-4" H="400" /><S Y="-25" T="12" P="0,0,0.3,0.2,0,0,0,0" L="1060" o="324650" m="" X="532" H="47" /><S N="" Y="318" T="12" P="1,0,0.3,0.2,0,0,0,0" i="0,0,x_transformice/x_evt/x_evt_05/yelfrdge/tasse.png" L="13" o="324650" X="592" H="13" /><S N="" i="0,0,x_transformice/x_evt/x_evt_05/yelfrdge/tasse.png" T="12" H="13" P="1,0,0.3,0.2,0,0,0,0" Y="320" L="13" o="324650" X="655" /><S Y="330" T="12" P="0,0,0.3,0.2,370,0,0,0" L="10" o="db16cb" m="" X="348" H="20" /></S><D><DS Y="362" X="180" /></D><O><O Y="87" X="858" P="0" C="14" /><O Y="97" X="815" P="0" C="14" /><O Y="114" X="816" P="0" C="14" /><O Y="132" X="815" P="0" C="14" /><O Y="147" X="816" P="0" C="14" /><O Y="82" X="816" P="0" C="11" /><O Y="158" P="0" X="810" C="14" /><O Y="158" X="823" P="0" C="14" /><O Y="253" X="566" P="0" C="22" /></O></Z></C>